{
  "version": "4.0.0-beta.3",
  "flags": {},
  "shapes": [
    {
      "label": "Ethernet Socket",
      "score": null,
      "points": [
        [
          1035.3125,
          991.25
        ],
        [
          1049.0625,
          1125.0
        ],
        [
          1175.3125,
          1098.7500000000002
        ],
        [
          1155.3125,
          971.2499999999999
        ]
      ],
      "group_id": null,
      "description": "",
      "difficult": false,
      "shape_type": "polygon",
      "flags": {},
      "attributes": {},
      "kie_linking": []
    },
    {
      "label": "VGA Socket",
      "score": null,
      "points": [
        [
          889.9999999999999,
          377.5342465753425
        ],
        [
          915.2054794520549,
          721.6438356164383
        ],
        [
          1026.986301369863,
          705.2054794520548
        ],
        [
          998.4931506849315,
          383.013698630137
        ]
      ],
      "group_id": null,
      "description": "",
      "difficult": false,
      "shape_type": "polygon",
      "flags": {},
      "attributes": {},
      "kie_linking": []
    }
  ],
  "imagePath": "frame_000515.png",
  "imageData": null,
  "imageHeight": 1440,
  "imageWidth": 2560,
  "description": ""
}